alkivi/__init__.py
alkivi/google/__init__.py
alkivi/google/client.py
alkivi/google/config.py
alkivi/google/credentials.py
alkivi_google_client-1.0.5.dist-info/METADATA
alkivi_google_client-1.0.5.dist-info/RECORD
alkivi_google_client-1.0.5.dist-info/WHEEL
alkivi_google_client-1.0.5.dist-info/top_level.txt
