Metadata-Version: 2.1
Name: alkivi-google-client
Version: 1.0.5
Summary: Google python client used at Alkivi
Home-page: https://github.com/alkivi-sas/python-alkivi-google-client
Author: Anthony Martinet
Author-email: anthony@alkivi.fr
License: LGPLv3
Keywords: alkivi google
Platform: UNKNOWN
Classifier: Development Status :: 4 - Beta
Classifier: Environment :: Console
Classifier: Intended Audience :: Developers
Classifier: Topic :: Software Development :: Build Tools
Classifier: License :: OSI Approved :: GNU Lesser General Public License v3 (LGPLv3)
Classifier: Programming Language :: Python :: 2
Classifier: Programming Language :: Python :: 2.7
Classifier: Programming Language :: Python :: 3
Classifier: Programming Language :: Python :: 3.3
Classifier: Programming Language :: Python :: 3.4
Classifier: Programming Language :: Python :: 3.5
Provides-Extra: dev
Provides-Extra: test
Requires-Dist: google-api-python-client
Requires-Dist: alkivi-logger
Requires-Dist: oauth2client
Provides-Extra: dev
Provides-Extra: test
